{"_via_settings":{"ui":{"annotation_editor_height":25,"annotation_editor_fontsize":0.8,"leftsidebar_width":18,"image_grid":{"img_height":80,"rshape_fill":"none","rshape_fill_opacity":0.3,"rshape_stroke":"yellow","rshape_stroke_width":2,"show_region_shape":true,"show_image_policy":"all"},"image":{"region_label":"__via_region_id__","region_color":"__via_default_region_color__","region_label_font":"10px Sans","on_image_annotation_editor_placement":"NEAR_REGION"}},"core":{"buffer_size":18,"filepath":{},"default_filepath":""},"project":{"name":"Daniel_Valcarce"}},"_via_img_metadata":{"ricard.jpg235123":{"filename":"ricard.jpg","size":235123,"regions":[{"shape_attributes":{"name":"rect","x":412,"y":64,"width":284,"height":418},"region_attributes":{"nom":"1"}},{"shape_attributes":{"name":"point","cx":604,"cy":258},"region_attributes":{"nom":"21"}},{"shape_attributes":{"name":"point","cx":559,"cy":307},"region_attributes":{"nom":"22"}},{"shape_attributes":{"name":"point","cx":560,"cy":372},"region_attributes":{"nom":"23"}},{"shape_attributes":{"name":"point","cx":506,"cy":263},"region_attributes":{"nom":"21"}}],"file_attributes":{"caption":"","public_domain":"no","image_url":""}},"img_1.jpg92469":{"filename":"img_1.jpg","size":92469,"regions":[{"shape_attributes":{"name":"rect","x":346,"y":74,"width":253,"height":392},"region_attributes":{"nom":"18"}},{"shape_attributes":{"name":"point","cx":421,"cy":251},"region_attributes":{"nom":"21"}},{"shape_attributes":{"name":"point","cx":526,"cy":261},"region_attributes":{"nom":"21"}},{"shape_attributes":{"name":"point","cx":472,"cy":334},"region_attributes":{"nom":"22"}},{"shape_attributes":{"name":"point","cx":469,"cy":389},"region_attributes":{"nom":"23"}}],"file_attributes":{"caption":"","public_domain":"no","image_url":""}},"img_2.jpg74625":{"filename":"img_2.jpg","size":74625,"regions":[{"shape_attributes":{"name":"rect","x":391,"y":74,"width":212,"height":287},"region_attributes":{"nom":"18"}},{"shape_attributes":{"name":"point","cx":446,"cy":183},"region_attributes":{"nom":"21"}},{"shape_attributes":{"name":"point","cx":529,"cy":186},"region_attributes":{"nom":"21"}},{"shape_attributes":{"name":"point","cx":491,"cy":234},"region_attributes":{"nom":"22"}},{"shape_attributes":{"name":"point","cx":490,"cy":289},"region_attributes":{"nom":"23"}}],"file_attributes":{"caption":"","public_domain":"no","image_url":""}},"img_3.jpg75650":{"filename":"img_3.jpg","size":75650,"regions":[{"shape_attributes":{"name":"rect","x":397,"y":115,"width":195,"height":270},"region_attributes":{"nom":"18"}},{"shape_attributes":{"name":"point","cx":455,"cy":225},"region_attributes":{"nom":"21"}},{"shape_attributes":{"name":"point","cx":529,"cy":231},"region_attributes":{"nom":"21"}},{"shape_attributes":{"name":"point","cx":493,"cy":274},"region_attributes":{"nom":"22"}},{"shape_attributes":{"name":"point","cx":489,"cy":321},"region_attributes":{"nom":"23"}}],"file_attributes":{"caption":"","public_domain":"no","image_url":""}},"img_4.jpg72050":{"filename":"img_4.jpg","size":72050,"regions":[{"shape_attributes":{"name":"rect","x":404,"y":142,"width":169,"height":244},"region_attributes":{"nom":"18"}},{"shape_attributes":{"name":"point","cx":483,"cy":257},"region_attributes":{"nom":"21"}},{"shape_attributes":{"name":"point","cx":547,"cy":265},"region_attributes":{"nom":"21"}},{"shape_attributes":{"name":"point","cx":526,"cy":311},"region_attributes":{"nom":"22"}},{"shape_attributes":{"name":"point","cx":511,"cy":347},"region_attributes":{"nom":"23"}}],"file_attributes":{"caption":"","public_domain":"no","image_url":""}},"img_5.jpg70967":{"filename":"img_5.jpg","size":70967,"regions":[{"shape_attributes":{"name":"rect","x":399,"y":126,"width":186,"height":270},"region_attributes":{"nom":"18"}},{"shape_attributes":{"name":"point","cx":463,"cy":256},"region_attributes":{"nom":"21"}},{"shape_attributes":{"name":"point","cx":533,"cy":261},"region_attributes":{"nom":"21"}},{"shape_attributes":{"name":"point","cx":503,"cy":308},"region_attributes":{"nom":"22"}},{"shape_attributes":{"name":"point","cx":495,"cy":351},"region_attributes":{"nom":"23"}}],"file_attributes":{"caption":"","public_domain":"no","image_url":""}},"img_6.jpg74839":{"filename":"img_6.jpg","size":74839,"regions":[{"shape_attributes":{"name":"rect","x":457,"y":106,"width":216,"height":315},"region_attributes":{"nom":"18"}},{"shape_attributes":{"name":"point","cx":556,"cy":292},"region_attributes":{"nom":"21"}},{"shape_attributes":{"name":"point","cx":635,"cy":295},"region_attributes":{"nom":"21"}},{"shape_attributes":{"name":"point","cx":606,"cy":361},"region_attributes":{"nom":"22"}},{"shape_attributes":{"name":"point","cx":589,"cy":390},"region_attributes":{"nom":"23"}}],"file_attributes":{"caption":"","public_domain":"no","image_url":""}},"img_7.jpg74799":{"filename":"img_7.jpg","size":74799,"regions":[{"shape_attributes":{"name":"rect","x":454,"y":28,"width":223,"height":325},"region_attributes":{"nom":"18"}},{"shape_attributes":{"name":"point","cx":481,"cy":186},"region_attributes":{"nom":"21"}},{"shape_attributes":{"name":"point","cx":557,"cy":191},"region_attributes":{"nom":"21"}},{"shape_attributes":{"name":"point","cx":504,"cy":246},"region_attributes":{"nom":"22"}},{"shape_attributes":{"name":"point","cx":518,"cy":295},"region_attributes":{"nom":"23"}}],"file_attributes":{"caption":"","public_domain":"no","image_url":""}},"img_8.jpg69465":{"filename":"img_8.jpg","size":69465,"regions":[{"shape_attributes":{"name":"rect","x":482,"y":138,"width":179,"height":248},"region_attributes":{"nom":"18"}},{"shape_attributes":{"name":"point","cx":563,"cy":244},"region_attributes":{"nom":"21"}},{"shape_attributes":{"name":"point","cx":629,"cy":256},"region_attributes":{"nom":"21"}},{"shape_attributes":{"name":"point","cx":611,"cy":297},"region_attributes":{"nom":"22"}},{"shape_attributes":{"name":"point","cx":600,"cy":335},"region_attributes":{"nom":"23"}}],"file_attributes":{"caption":"","public_domain":"no","image_url":""}},"img_9.jpg77135":{"filename":"img_9.jpg","size":77135,"regions":[{"shape_attributes":{"name":"rect","x":435,"y":108,"width":202,"height":242},"region_attributes":{"nom":"18"}},{"shape_attributes":{"name":"point","cx":450,"cy":216},"region_attributes":{"nom":"21"}},{"shape_attributes":{"name":"point","cx":505,"cy":195},"region_attributes":{"nom":"21"}},{"shape_attributes":{"name":"point","cx":456,"cy":234},"region_attributes":{"nom":"22"}},{"shape_attributes":{"name":"point","cx":480,"cy":283},"region_attributes":{"nom":"23"}}],"file_attributes":{"caption":"","public_domain":"no","image_url":""}},"img_10.jpg83725":{"filename":"img_10.jpg","size":83725,"regions":[{"shape_attributes":{"name":"rect","x":477,"y":138,"width":157,"height":183},"region_attributes":{"nom":"18"}},{"shape_attributes":{"name":"point","cx":544,"cy":194},"region_attributes":{"nom":"21"}},{"shape_attributes":{"name":"point","cx":602,"cy":202},"region_attributes":{"nom":"21"}},{"shape_attributes":{"name":"point","cx":579,"cy":212},"region_attributes":{"nom":"22"}},{"shape_attributes":{"name":"point","cx":574,"cy":255},"region_attributes":{"nom":"23"}}],"file_attributes":{"caption":"","public_domain":"no","image_url":""}},"img_11.jpg87916":{"filename":"img_11.jpg","size":87916,"regions":[{"shape_attributes":{"name":"rect","x":383,"y":4,"width":246,"height":339},"region_attributes":{"nom":"18"}},{"shape_attributes":{"name":"point","cx":452,"cy":116},"region_attributes":{"nom":"21"}},{"shape_attributes":{"name":"point","cx":549,"cy":121},"region_attributes":{"nom":"21"}},{"shape_attributes":{"name":"point","cx":500,"cy":158},"region_attributes":{"nom":"22"}},{"shape_attributes":{"name":"point","cx":496,"cy":233},"region_attributes":{"nom":"23"}}],"file_attributes":{"caption":"","public_domain":"no","image_url":""}},"img_12.jpg86021":{"filename":"img_12.jpg","size":86021,"regions":[{"shape_attributes":{"name":"rect","x":483,"y":96,"width":193,"height":198},"region_attributes":{"nom":"18"}},{"shape_attributes":{"name":"point","cx":499,"cy":174},"region_attributes":{"nom":"21"}},{"shape_attributes":{"name":"point","cx":554,"cy":150},"region_attributes":{"nom":"21"}},{"shape_attributes":{"name":"point","cx":506,"cy":184},"region_attributes":{"nom":"22"}},{"shape_attributes":{"name":"point","cx":528,"cy":225},"region_attributes":{"nom":"23"}}],"file_attributes":{"caption":"","public_domain":"no","image_url":""}},"img_13.jpg72040":{"filename":"img_13.jpg","size":72040,"regions":[{"shape_attributes":{"name":"rect","x":249,"y":107,"width":297,"height":374},"region_attributes":{"nom":"18"}},{"shape_attributes":{"name":"point","cx":466,"cy":269},"region_attributes":{"nom":"21"}},{"shape_attributes":{"name":"point","cx":539,"cy":349},"region_attributes":{"nom":"22"}},{"shape_attributes":{"name":"point","cx":497,"cy":405},"region_attributes":{"nom":"23"}}],"file_attributes":{"caption":"","public_domain":"no","image_url":""}},"img_14.jpg86229":{"filename":"img_14.jpg","size":86229,"regions":[{"shape_attributes":{"name":"rect","x":318,"y":1,"width":294,"height":412},"region_attributes":{"nom":"18"}},{"shape_attributes":{"name":"point","cx":464,"cy":172},"region_attributes":{"nom":"21"}},{"shape_attributes":{"name":"point","cx":570,"cy":193},"region_attributes":{"nom":"21"}},{"shape_attributes":{"name":"point","cx":543,"cy":262},"region_attributes":{"nom":"22"}},{"shape_attributes":{"name":"point","cx":517,"cy":327},"region_attributes":{"nom":"23"}}],"file_attributes":{"caption":"","public_domain":"no","image_url":""}},"img_15.jpg70786":{"filename":"img_15.jpg","size":70786,"regions":[{"shape_attributes":{"name":"rect","x":320,"y":100,"width":225,"height":313},"region_attributes":{"nom":"18"}},{"shape_attributes":{"name":"point","cx":386,"cy":226},"region_attributes":{"nom":"21"}},{"shape_attributes":{"name":"point","cx":475,"cy":233},"region_attributes":{"nom":"21"}},{"shape_attributes":{"name":"point","cx":435,"cy":279},"region_attributes":{"nom":"22"}},{"shape_attributes":{"name":"point","cx":433,"cy":339},"region_attributes":{"nom":"23"}}],"file_attributes":{"caption":"","public_domain":"no","image_url":""}},"img_16.jpg76893":{"filename":"img_16.jpg","size":76893,"regions":[{"shape_attributes":{"name":"rect","x":534,"y":137,"width":174,"height":221},"region_attributes":{"nom":"18"}},{"shape_attributes":{"name":"point","cx":649,"cy":221},"region_attributes":{"nom":"21"}},{"shape_attributes":{"name":"point","cx":693,"cy":236},"region_attributes":{"nom":"21"}},{"shape_attributes":{"name":"point","cx":693,"cy":266},"region_attributes":{"nom":"22"}},{"shape_attributes":{"name":"point","cx":673,"cy":305},"region_attributes":{"nom":"23"}}],"file_attributes":{"caption":"","public_domain":"no","image_url":""}},"img_17.jpg70690":{"filename":"img_17.jpg","size":70690,"regions":[{"shape_attributes":{"name":"rect","x":502,"y":107,"width":221,"height":312},"region_attributes":{"nom":"18"}},{"shape_attributes":{"name":"point","cx":632,"cy":289},"region_attributes":{"nom":"21"}},{"shape_attributes":{"name":"point","cx":697,"cy":285},"region_attributes":{"nom":"21"}},{"shape_attributes":{"name":"point","cx":687,"cy":354},"region_attributes":{"nom":"22"}},{"shape_attributes":{"name":"point","cx":660,"cy":384},"region_attributes":{"nom":"23"}}],"file_attributes":{"caption":"","public_domain":"no","image_url":""}},"img_18.jpg92948":{"filename":"img_18.jpg","size":92948,"regions":[{"shape_attributes":{"name":"rect","x":369,"y":43,"width":309,"height":407},"region_attributes":{"nom":"18"}},{"shape_attributes":{"name":"point","cx":396,"cy":230},"region_attributes":{"nom":"21"}},{"shape_attributes":{"name":"point","cx":483,"cy":221},"region_attributes":{"nom":"21"}},{"shape_attributes":{"name":"point","cx":401,"cy":308},"region_attributes":{"nom":"22"}},{"shape_attributes":{"name":"point","cx":430,"cy":370},"region_attributes":{"nom":"23"}}],"file_attributes":{"caption":"","public_domain":"no","image_url":""}},"img_19.jpg68029":{"filename":"img_19.jpg","size":68029,"regions":[{"shape_attributes":{"name":"rect","x":443,"y":119,"width":216,"height":335},"region_attributes":{"nom":"18"}},{"shape_attributes":{"name":"point","cx":539,"cy":311},"region_attributes":{"nom":"21"}},{"shape_attributes":{"name":"point","cx":621,"cy":306},"region_attributes":{"nom":"21"}},{"shape_attributes":{"name":"point","cx":594,"cy":382},"region_attributes":{"nom":"22"}},{"shape_attributes":{"name":"point","cx":588,"cy":413},"region_attributes":{"nom":"23"}}],"file_attributes":{"caption":"","public_domain":"no","image_url":""}},"img_20.jpg69031":{"filename":"img_20.jpg","size":69031,"regions":[{"shape_attributes":{"name":"rect","x":317,"y":141,"width":251,"height":292},"region_attributes":{"nom":"18"}},{"shape_attributes":{"name":"point","cx":524,"cy":280},"region_attributes":{"nom":"21"}},{"shape_attributes":{"name":"point","cx":563,"cy":338},"region_attributes":{"nom":"22"}},{"shape_attributes":{"name":"point","cx":529,"cy":376},"region_attributes":{"nom":"23"}}],"file_attributes":{"caption":"","public_domain":"no","image_url":""}},"img_21.jpg83586":{"filename":"img_21.jpg","size":83586,"regions":[{"shape_attributes":{"name":"rect","x":448,"y":97,"width":181,"height":231},"region_attributes":{"nom":"18"}},{"shape_attributes":{"name":"point","cx":547,"cy":174},"region_attributes":{"nom":"21"}},{"shape_attributes":{"name":"point","cx":606,"cy":191},"region_attributes":{"nom":"21"}},{"shape_attributes":{"name":"point","cx":595,"cy":214},"region_attributes":{"nom":"22"}},{"shape_attributes":{"name":"point","cx":576,"cy":259},"region_attributes":{"nom":"23"}}],"file_attributes":{"caption":"","public_domain":"no","image_url":""}},"img_22.jpg66285":{"filename":"img_22.jpg","size":66285,"regions":[{"shape_attributes":{"name":"rect","x":378,"y":227,"width":158,"height":214},"region_attributes":{"nom":"18"}},{"shape_attributes":{"name":"point","cx":422,"cy":306},"region_attributes":{"nom":"21"}},{"shape_attributes":{"name":"point","cx":483,"cy":318},"region_attributes":{"nom":"21"}},{"shape_attributes":{"name":"point","cx":445,"cy":347},"region_attributes":{"nom":"22"}},{"shape_attributes":{"name":"point","cx":442,"cy":386},"region_attributes":{"nom":"23"}}],"file_attributes":{"caption":"","public_domain":"no","image_url":""}},"img_23.jpg88185":{"filename":"img_23.jpg","size":88185,"regions":[{"shape_attributes":{"name":"rect","x":456,"y":152,"width":198,"height":292},"region_attributes":{"nom":"18"}},{"shape_attributes":{"name":"point","cx":515,"cy":288},"region_attributes":{"nom":"21"}},{"shape_attributes":{"name":"point","cx":592,"cy":288},"region_attributes":{"nom":"21"}},{"shape_attributes":{"name":"point","cx":556,"cy":342},"region_attributes":{"nom":"22"}},{"shape_attributes":{"name":"point","cx":554,"cy":389},"region_attributes":{"nom":"23"}}],"file_attributes":{"caption":"","public_domain":"no","image_url":""}},"img_24.jpg91687":{"filename":"img_24.jpg","size":91687,"regions":[{"shape_attributes":{"name":"rect","x":384,"y":165,"width":247,"height":339},"region_attributes":{"nom":"18"}},{"shape_attributes":{"name":"point","cx":401,"cy":348},"region_attributes":{"nom":"21"}},{"shape_attributes":{"name":"point","cx":466,"cy":365},"region_attributes":{"nom":"21"}},{"shape_attributes":{"name":"point","cx":403,"cy":427},"region_attributes":{"nom":"22"}},{"shape_attributes":{"name":"point","cx":429,"cy":458},"region_attributes":{"nom":"23"}}],"file_attributes":{"caption":"","public_domain":"no","image_url":""}},"img_25.jpg69088":{"filename":"img_25.jpg","size":69088,"regions":[{"shape_attributes":{"name":"rect","x":476,"y":184,"width":280,"height":316},"region_attributes":{"nom":"18"}},{"shape_attributes":{"name":"point","cx":524,"cy":372},"region_attributes":{"nom":"21"}},{"shape_attributes":{"name":"point","cx":481,"cy":412},"region_attributes":{"nom":"22"}},{"shape_attributes":{"name":"point","cx":516,"cy":449},"region_attributes":{"nom":"23"}}],"file_attributes":{"caption":"","public_domain":"no","image_url":""}},"img_26.jpg76931":{"filename":"img_26.jpg","size":76931,"regions":[{"shape_attributes":{"name":"rect","x":350,"y":161,"width":254,"height":289},"region_attributes":{"nom":"18"}},{"shape_attributes":{"name":"point","cx":406,"cy":294},"region_attributes":{"nom":"21"}},{"shape_attributes":{"name":"point","cx":356,"cy":347},"region_attributes":{"nom":"22"}},{"shape_attributes":{"name":"point","cx":383,"cy":392},"region_attributes":{"nom":"23"}}],"file_attributes":{"caption":"","public_domain":"no","image_url":""}},"img_27.jpg74242":{"filename":"img_27.jpg","size":74242,"regions":[{"shape_attributes":{"name":"rect","x":348,"y":223,"width":234,"height":299},"region_attributes":{"nom":"18"}},{"shape_attributes":{"name":"point","cx":491,"cy":335},"region_attributes":{"nom":"21"}},{"shape_attributes":{"name":"point","cx":563,"cy":346},"region_attributes":{"nom":"21"}},{"shape_attributes":{"name":"point","cx":562,"cy":392},"region_attributes":{"nom":"22"}},{"shape_attributes":{"name":"point","cx":541,"cy":450},"region_attributes":{"nom":"23"}}],"file_attributes":{"caption":"","public_domain":"no","image_url":""}},"img_28.jpg71569":{"filename":"img_28.jpg","size":71569,"regions":[{"shape_attributes":{"name":"rect","x":317,"y":109,"width":219,"height":307},"region_attributes":{"nom":"18"}},{"shape_attributes":{"name":"point","cx":413,"cy":231},"region_attributes":{"nom":"21"}},{"shape_attributes":{"name":"point","cx":496,"cy":242},"region_attributes":{"nom":"21"}},{"shape_attributes":{"name":"point","cx":474,"cy":287},"region_attributes":{"nom":"22"}},{"shape_attributes":{"name":"point","cx":459,"cy":342},"region_attributes":{"nom":"23"}}],"file_attributes":{"caption":"","public_domain":"no","image_url":""}},"img_29.jpg76692":{"filename":"img_29.jpg","size":76692,"regions":[{"shape_attributes":{"name":"rect","x":379,"y":9,"width":339,"height":472},"region_attributes":{"nom":"18"}},{"shape_attributes":{"name":"point","cx":426,"cy":192},"region_attributes":{"nom":"21"}},{"shape_attributes":{"name":"point","cx":552,"cy":201},"region_attributes":{"nom":"21"}},{"shape_attributes":{"name":"point","cx":443,"cy":276},"region_attributes":{"nom":"22"}},{"shape_attributes":{"name":"point","cx":455,"cy":366},"region_attributes":{"nom":"23"}}],"file_attributes":{"caption":"","public_domain":"no","image_url":""}},"img_30.jpg79470":{"filename":"img_30.jpg","size":79470,"regions":[{"shape_attributes":{"name":"rect","x":455,"y":109,"width":178,"height":245},"region_attributes":{"nom":"18"}},{"shape_attributes":{"name":"point","cx":505,"cy":203},"region_attributes":{"nom":"21"}},{"shape_attributes":{"name":"point","cx":574,"cy":211},"region_attributes":{"nom":"21"}},{"shape_attributes":{"name":"point","cx":536,"cy":243},"region_attributes":{"nom":"22"}},{"shape_attributes":{"name":"point","cx":527,"cy":288},"region_attributes":{"nom":"23"}}],"file_attributes":{"caption":"","public_domain":"no","image_url":""}}},"_via_attributes":{"region":{"nom":{"type":"radio","description":"Name of the object","options":{"1":"Desconegut","2":"AndreaInsabato","3":"VicentePallares","4":"GerardAlcover","5":"RogerRoca","6":"EnriqueGraziano","7":"VictorSteiner","8":"GenisHeredia","9":"FranciscoMartin","10":"ChrisMatienzo","11":"MarcRoig","12":"FerranPrat","13":"JosepCarreras","14":"MarcelSerra","15":"JordiCasals","16":"OriolJulia","17":"PereClaver","18":"DanielValcarce","19":"RicardPeralta","20":"MarcRodriguez","21":"ull","22":"nas","23":"boca"},"default_options":{"1":true}}},"file":{"caption":{"type":"text","description":"","default_value":""},"public_domain":{"type":"radio","description":"","options":{"yes":"Yes","no":"No"},"default_options":{"no":true}},"image_url":{"type":"text","description":"","default_value":""}}}}